LICENSE.TXT
MANIFEST.in
README.md
setup.py
external/gcem/.appveyor.yml
external/gcem/.git
external/gcem/.gitignore
external/gcem/.lgtm.yml
external/gcem/.readthedocs.requirements.txt
external/gcem/.readthedocs.yml
external/gcem/.travis.yml
external/gcem/CMakeLists.txt
external/gcem/LICENSE
external/gcem/NOTICE.txt
external/gcem/README.md
external/gcem/contributors.txt
external/gcem/.github/workflows/main.yml
external/gcem/binder/environment.yml
external/gcem/cmake_files/gcemConfig.cmake.in
external/gcem/docs/Doxyfile
external/gcem/docs/Makefile
external/gcem/docs/environment.yml
external/gcem/docs/make.bat
external/gcem/docs/source/conf.py
external/gcem/docs/source/examples.rst
external/gcem/docs/source/index.rst
external/gcem/docs/source/_static/main_stylesheet.css
external/gcem/docs/source/api/algorithms.rst
external/gcem/docs/source/api/basic_functions.rst
external/gcem/docs/source/api/hyperbolic_functions.rst
external/gcem/docs/source/api/math_index.rst
external/gcem/docs/source/api/special_functions.rst
external/gcem/docs/source/api/trigonometric_functions.rst
external/gcem/include/gcem.hpp
external/gcem/include/gcem_incl/abs.hpp
external/gcem/include/gcem_incl/acos.hpp
external/gcem/include/gcem_incl/acosh.hpp
external/gcem/include/gcem_incl/asin.hpp
external/gcem/include/gcem_incl/asinh.hpp
external/gcem/include/gcem_incl/atan.hpp
external/gcem/include/gcem_incl/atan2.hpp
external/gcem/include/gcem_incl/atanh.hpp
external/gcem/include/gcem_incl/beta.hpp
external/gcem/include/gcem_incl/binomial_coef.hpp
external/gcem/include/gcem_incl/ceil.hpp
external/gcem/include/gcem_incl/copysign.hpp
external/gcem/include/gcem_incl/cos.hpp
external/gcem/include/gcem_incl/cosh.hpp
external/gcem/include/gcem_incl/erf.hpp
external/gcem/include/gcem_incl/erf_inv.hpp
external/gcem/include/gcem_incl/exp.hpp
external/gcem/include/gcem_incl/expm1.hpp
external/gcem/include/gcem_incl/factorial.hpp
external/gcem/include/gcem_incl/find_exponent.hpp
vara_feature.egg-info/PKG-INFO
vara_feature.egg-info/SOURCES.txt
vara_feature.egg-info/dependency_links.txt
vara_feature.egg-info/not-zip-safe
vara_feature.egg-info/top_level.txt