Metadata-Version: 2.1
Name: vara-feature
Version: 11.1.2
Summary: Python bindings for vara-feature library
Home-page: UNKNOWN
Author: Florian Sattler
Author-email: sattlerf@cs.uni-saarland.de
License: LICENSE.TXT
Platform: UNKNOWN
Requires-Python: >=3.6
License-File: LICENSE.TXT
